Metadata-Version: 2.1
Name: LC-package
Version: 0.2
Summary: LC Python package
License-File: LICENSE
